LICENSE
README.md
setup.py
ctmd/__init__.py
ctmd.egg-info/PKG-INFO
ctmd.egg-info/SOURCES.txt
ctmd.egg-info/dependency_links.txt
ctmd.egg-info/top_level.txt