Metadata-Version: 2.1
Name: ctmd
Version: 0.0.0
Summary: ctmd
Home-page: https://github.com/Kaguya233qwq/ctmd
Author: Kaguya233qwq
Author-email: 1435608435@qq.com
License: UNKNOWN
Keywords: ctmd,传统美德
Platform: any
Classifier: Programming Language :: Python :: 3
Classifier: License :: OSI Approved :: GNU General Public License v3 (GPLv3)
Classifier: Natural Language :: Chinese (Simplified)
License-File: LICENSE
